bitarray/__init__.py
bitarray/__init__.pyi
bitarray/_bitarray.cpython-38-x86_64-linux-gnu.so
bitarray/_util.cpython-38-x86_64-linux-gnu.so
bitarray/bitarray.h
bitarray/py.typed
bitarray/pythoncapi_compat.h
bitarray/test_bitarray.py
bitarray/test_data.pickle
bitarray/test_util.py
bitarray/util.py
bitarray/util.pyi
bitarray_binary-2.3.4.dist-info/METADATA
bitarray_binary-2.3.4.dist-info/WHEEL
bitarray_binary-2.3.4.dist-info/top_level.txt
bitarray_binary-2.3.4.dist-info/RECORD
